turboflow/__init__.py
turboflow/axial_turbine/__init__.py
turboflow/axial_turbine/choking_criterion.py
turboflow/axial_turbine/design_optimization.py
turboflow/axial_turbine/deviation_model.py
turboflow/axial_turbine/flow_model.py
turboflow/axial_turbine/geometry_model.py
turboflow/axial_turbine/loss_model.py
turboflow/axial_turbine/loss_model_benner.py
turboflow/axial_turbine/loss_model_kacker_okapuu.py
turboflow/axial_turbine/loss_model_moustapha.py
turboflow/axial_turbine/performance_analysis.py
turboflow/centrifugal_compressor/__init__.py
turboflow/centrifugal_compressor/choking_criterion.py
turboflow/centrifugal_compressor/flow_model.py
turboflow/centrifugal_compressor/geometry_model.py
turboflow/centrifugal_compressor/loss_model.py
turboflow/centrifugal_compressor/loss_model_custom.py
turboflow/centrifugal_compressor/loss_model_oh.py
turboflow/centrifugal_compressor/loss_model_zhang_set1.py
turboflow/centrifugal_compressor/loss_model_zhang_set2.py
turboflow/centrifugal_compressor/loss_model_zhang_set3.py
turboflow/centrifugal_compressor/performance_analysis.py
turboflow/centrifugal_compressor/slip_model.py
turboflow/config_validation.py
turboflow/math.py
turboflow/plot_functions.py
turboflow/properties/__init__.py
turboflow/properties/fluid_properties.py
turboflow/pysolver_view/__init__.py
turboflow/pysolver_view/nonlinear_system.py
turboflow/pysolver_view/nonlinear_system_problems.py
turboflow/pysolver_view/numerical_differentiation.py
turboflow/pysolver_view/optimization.py
turboflow/pysolver_view/optimization_problems.py
turboflow/pysolver_view/optimization_wrappers.py
turboflow/pysolver_view/pysolver_utilities.py
turboflow/turbo_configurations/__init__.py
turboflow/turbo_configurations/config_axial_turbine.py
turboflow/turbo_configurations/config_centrifugal_compressor.py
turboflow/utilities/__init__.py
turboflow/utilities/file_utils.py
turboflow/utilities/graphics.py
turboflow/utilities/numerics.py
turboflow/utilities/optimization_utils.py
turboflow-0.1.18.dist-info/LICENSE.md
turboflow-0.1.18.dist-info/METADATA
turboflow-0.1.18.dist-info/WHEEL
turboflow-0.1.18.dist-info/RECORD
