Metadata-Version: 2.3
Name: turboflow
Version: 0.1.18
Summary: A Python tool for meanline analysis and optimization of turbomachinery.
License: MIT
Author: Lasse Borg & Roberto Agromayor
Requires-Python: >=3.11,<4.0
Classifier: License :: OSI Approved :: MIT License
Classifier: Programming Language :: Python :: 3
Classifier: Programming Language :: Python :: 3.11
Classifier: Programming Language :: Python :: 3.12
Classifier: Programming Language :: Python :: 3.13
Requires-Dist: CoolProp (>=6.6.0,<7.0.0)
Requires-Dist: PyYAML (>=6.0.1,<7.0.0)
Requires-Dist: certifi (>=2025.1.31,<2026.0.0)
Requires-Dist: cycler (>=0.12.1,<0.13.0)
Requires-Dist: jinja2 (>=3.1.6,<4.0.0)
Requires-Dist: matplotlib (>=3.9.0,<4.0.0)
Requires-Dist: numpy (>=1.26.4,<2.0.0)
Requires-Dist: openpyxl (>=3.1.2,<4.0.0)
Requires-Dist: pandas (>=2.2.2,<3.0.0)
Requires-Dist: pydantic (>=2.7.2,<3.0.0)
Requires-Dist: scipy (>=1.13.1,<2.0.0)
Requires-Dist: toml (>=0.10.2,<0.11.0)
Requires-Dist: urllib3 (>=2.3.0,<3.0.0)
Project-URL: Documentation, https://turbo-sim.github.io/TurboFlow/
Project-URL: Repository, https://github.com/turbo-sim/TurboFlow
